grafana_weaver/__init__.py
grafana_weaver/main.py
grafana_weaver/core/__init__.py
grafana_weaver/core/client.py
grafana_weaver/core/config_manager.py
grafana_weaver/core/dashboard_downloader.py
grafana_weaver/core/dashboard_extractor.py
grafana_weaver/core/jsonnet_builder.py
grafana_weaver-0.1.8.dist-info/METADATA
grafana_weaver-0.1.8.dist-info/WHEEL
grafana_weaver-0.1.8.dist-info/entry_points.txt
grafana_weaver-0.1.8.dist-info/licenses/LICENSE
grafana_weaver-0.1.8.dist-info/RECORD
