Metadata-Version: 2.4
Name: grafana-weaver
Version: 0.1.8
Summary: A system for managing Grafana dashboards as code using Jsonnet
Project-URL: Homepage, https://github.com/rhiza-research/grafana-weaver
Project-URL: Repository, https://github.com/rhiza-research/grafana-weaver
Project-URL: Issues, https://github.com/rhiza-research/grafana-weaver/issues
Author-email: Rhiza Research <info@rhizaresearch.org>
License: MIT
License-File: LICENSE
Keywords: dashboards,grafana,infrastructure-as-code,jsonnet,terraform
Classifier: Development Status :: 4 - Beta
Classifier: Intended Audience :: Developers
Classifier: License :: OSI Approved :: MIT License
Classifier: Programming Language :: Python :: 3
Classifier: Programming Language :: Python :: 3.10
Classifier: Programming Language :: Python :: 3.11
Classifier: Programming Language :: Python :: 3.12
Classifier: Topic :: Software Development :: Libraries :: Python Modules
Requires-Python: >=3.10
Requires-Dist: jsonnet>=0.20.0
Requires-Dist: pyyaml>=6.0
Requires-Dist: requests>=2.31.0
Provides-Extra: dev
Requires-Dist: pytest-cov>=4.0.0; extra == 'dev'
Requires-Dist: pytest-mock>=3.10.0; extra == 'dev'
Requires-Dist: pytest>=7.0.0; extra == 'dev'
Requires-Dist: ruff>=0.1.0; extra == 'dev'
